{"fetched_at": 1783709281.491055, "data": {"sector": "Industrials", "industry": "Aerospace & Defense", "marketCap": 162914615296, "returnOnEquity": -0.102919996, "returnOnAssets": -0.013359999, "profitMargins": -0.09204, "operatingMargins": -0.11249, "revenueGrowth": 0.473, "earningsGrowth": null, "debtToEquity": 47.183, "trailingPE": null, "forwardPE": 382.73846, "pegRatio": null, "priceToBook": 10.10192, "bookValue": 24.627, "enterpriseToEbitda": 172.445, "enterpriseValue": 153598689280, "ebitda": 890710016, "fiftyTwoWeekHigh": 274.39, "fiftyTwoWeekLow": 113.3, "freeCashflow": -3981367552, "heldPercentInsiders": 0.73466, "heldPercentInstitutions": 0.14097, "currentRatio": 1.584, "quickRatio": 0.766, "totalDebt": 7009310208, "totalCash": 3566520064}}