{"fetched_at": 1783709309.613662, "data": {"sector": "Healthcare", "industry": "Medical Distribution", "marketCap": 52702089216, "returnOnEquity": 0.0828, "returnOnAssets": 0.044159997, "profitMargins": 0.01745, "operatingMargins": 0.03731, "revenueGrowth": 0.426, "earningsGrowth": 0.091, "debtToEquity": 38.638, "trailingPE": 45.867424, "forwardPE": 21.962458, "pegRatio": null, "priceToBook": 3.1188185, "bookValue": 388.256, "enterpriseToEbitda": 21.492, "enterpriseValue": 57158877184, "ebitda": 2659549952, "fiftyTwoWeekHigh": 1390.0, "fiftyTwoWeekLow": 944.0, "freeCashflow": 696771264, "heldPercentInsiders": 0.65920997, "heldPercentInstitutions": 0.14821, "currentRatio": 1.58, "quickRatio": 0.947, "totalDebt": 6771520000, "totalCash": 2916750080}}