{"fetched_at": 1783709319.1743722, "data": {"sector": "Industrials", "industry": "Marine Shipping", "marketCap": 74623467520, "returnOnEquity": 0.21802999, "returnOnAssets": 0.122150004, "profitMargins": 0.44472998, "operatingMargins": 0.60801, "revenueGrowth": 0.24, "earningsGrowth": 0.25, "debtToEquity": 1.544, "trailingPE": 14.474672, "forwardPE": 13.359307, "pegRatio": null, "priceToBook": 3.1677926, "bookValue": 48.709, "enterpriseToEbitda": 9.782, "enterpriseValue": 69269708800, "ebitda": 7081639936, "fiftyTwoWeekHigh": 200.09, "fiftyTwoWeekLow": 141.55, "freeCashflow": -526827488, "heldPercentInsiders": 0.44037998, "heldPercentInstitutions": 0.28698, "currentRatio": 2.538, "quickRatio": 1.728, "totalDebt": 368740000, "totalCash": 6759240192}}