{"fetched_at": 1783709326.426729, "data": {"sector": "Basic Materials", "industry": "Specialty Chemicals", "marketCap": 50173870080, "returnOnEquity": 0.13514, "returnOnAssets": 0.080019996, "profitMargins": 0.10326, "operatingMargins": 0.18871, "revenueGrowth": 0.097, "earningsGrowth": 0.013, "debtToEquity": 1.831, "trailingPE": 34.74414, "forwardPE": 25.207186, "pegRatio": null, "priceToBook": 4.3463717, "bookValue": 242.133, "enterpriseToEbitda": 18.466, "enterpriseValue": 47047340032, "ebitda": 2547718912, "fiftyTwoWeekHigh": 1345.9, "fiftyTwoWeekLow": 708.05, "freeCashflow": 758073984, "heldPercentInsiders": 0.53878, "heldPercentInstitutions": 0.27991, "currentRatio": 2.209, "quickRatio": 1.681, "totalDebt": 211304992, "totalCash": 3319696896}}