{"fetched_at": 1783709147.9882398, "data": {"sector": "Communication Services", "industry": "Telecom Services", "marketCap": 1071094628352, "returnOnEquity": 0.19806999, "returnOnAssets": 0.100710005, "profitMargins": 0.21989, "operatingMargins": 0.32422, "revenueGrowth": 0.048, "earningsGrowth": 0.008, "debtToEquity": 53.289, "trailingPE": 15.003695, "forwardPE": 13.051307, "pegRatio": null, "priceToBook": 2.701669, "bookValue": 150.333, "enterpriseToEbitda": 8.018, "enterpriseValue": 1223788593152, "ebitda": 152623005696, "fiftyTwoWeekHigh": 481.5, "fiftyTwoWeekLow": 312.55, "freeCashflow": 43259248640, "heldPercentInsiders": 0.51315, "heldPercentInstitutions": 0.30294, "currentRatio": 1.724, "quickRatio": 1.199, "totalDebt": 211268993024, "totalCash": 58574999552}}