{"fetched_at": 1783709153.8939462, "data": {"sector": "Basic Materials", "industry": "Building Materials", "marketCap": 417132642304, "returnOnEquity": 0.15032, "returnOnAssets": 0.06183, "profitMargins": 0.07225, "operatingMargins": 0.13306, "revenueGrowth": 0.082, "earningsGrowth": -0.076, "debtToEquity": 87.522, "trailingPE": 42.05422, "forwardPE": 28.42313, "pegRatio": 0.94, "priceToBook": 5.927493, "bookValue": 910.756, "enterpriseToEbitda": 19.804, "enterpriseValue": 469184151552, "ebitda": 23691399168, "fiftyTwoWeekHigh": 7565.5, "fiftyTwoWeekLow": 4671.5, "freeCashflow": -7735050240, "heldPercentInsiders": 0.54296, "heldPercentInstitutions": 0.36609, "currentRatio": 0.933, "quickRatio": 0.473, "totalDebt": 62055698432, "totalCash": 10534800384}}