{"fetched_at": 1783709168.560319, "data": {"sector": "Industrials", "industry": "Engineering & Construction", "marketCap": 134391070720, "returnOnEquity": 0.10524999, "returnOnAssets": 0.03858, "profitMargins": 0.02576, "operatingMargins": 0.06221, "revenueGrowth": -0.07, "earningsGrowth": -0.281, "debtToEquity": 87.306, "trailingPE": 22.210735, "forwardPE": 12.875828, "pegRatio": null, "priceToBook": 2.1824744, "bookValue": 231.32, "enterpriseToEbitda": 11.039, "enterpriseValue": 183092051968, "ebitda": 16585700352, "fiftyTwoWeekHigh": 937.8, "fiftyTwoWeekLow": 466.0, "freeCashflow": -18438062080, "heldPercentInsiders": 0.04563, "heldPercentInstitutions": 0.77516997, "currentRatio": 1.233, "quickRatio": 1.061, "totalDebt": 53777600512, "totalCash": 5119300096}}