{"fetched_at": 1783709387.186183, "data": {"sector": "Healthcare", "industry": "Drug Manufacturers - Specialty & Generic", "marketCap": 85868421120, "returnOnEquity": 2.7689402, "returnOnAssets": 0.79225, "profitMargins": 39.67305, "operatingMargins": 0.95553, "revenueGrowth": 67.168, "earningsGrowth": null, "debtToEquity": 41.776, "trailingPE": 5.529781, "forwardPE": 4.776173, "pegRatio": null, "priceToBook": 6.41439, "bookValue": 41.251, "enterpriseToEbitda": 5.721, "enterpriseValue": 91457781760, "ebitda": 15987600384, "fiftyTwoWeekHigh": 289.0, "fiftyTwoWeekLow": 108.0, "freeCashflow": -8949500928, "heldPercentInsiders": 0.75121003, "heldPercentInstitutions": 0.01827, "currentRatio": 2.47, "quickRatio": 0.02, "totalDebt": 5593099776, "totalCash": 11600000}}