{"fetched_at": 1783709277.068762, "data": {"sector": "Healthcare", "industry": "Drug Manufacturers - Specialty & Generic", "marketCap": 1147927396352, "returnOnEquity": 0.18318, "returnOnAssets": 0.08071999, "profitMargins": 0.18565, "operatingMargins": 0.18466999, "revenueGrowth": 0.162, "earningsGrowth": 0.087, "debtToEquity": 42.242, "trailingPE": 22.983824, "forwardPE": 24.405378, "pegRatio": null, "priceToBook": 4.2698765, "bookValue": 269.516, "enterpriseToEbitda": 17.022, "enterpriseValue": 1235366969344, "ebitda": 72576000000, "fiftyTwoWeekHigh": 1181.5, "fiftyTwoWeekLow": 835.5, "freeCashflow": 13310125056, "heldPercentInsiders": 0.75184995, "heldPercentInstitutions": 0.15035, "currentRatio": 1.267, "quickRatio": 0.802, "totalDebt": 124959997952, "totalCash": 71923998720}}